<theme>
<formatVersion>4</formatVersion>
<include>./../theme.xml</include>

<view name="basic, detailed, video, grid">
  <text name="nameLabel" extra="true">
    <text>Coleco Vision</text>
  </text>
</view>    

<view name="system">
  <text name="sys_line1" extra="true">
    <text>Coleco Industries, Inc.</text>
    <fontSize>0.040</fontSize>
    <origin>0 0</origin>
    <pos>0.025 0.142</pos>
    <size>0 0</size>
  </text>
  <text name="sys_line2" extra="true">
    <text>ColecoVision</text>
    <fontSize>0.15</fontSize>
    <origin>0 0</origin>
    <pos>0.025 0.16</pos>
    <size>0 0</size>
</text>
  <text name="shortdescription" extra="true">
   <text>1982  ·  8-BIT CONSOLE</text>
  </text>
  <text name="longdescription" extra="true">
   <text> A closer experience to more powerful arcade game systems. CPU Zilog Z80 Storage 8/16/24/32 KB, Graphics	TMS9928A, Joystick/Numeric Keypad, ROM cartridge. Retail avail. NA: Aug '82 EU: Jul '83.</text>
  </text>
 </view>
</theme>
